domintell/__init__.py
domintell/command.py
domintell/controller.py
domintell/message.py
domintell/module.py
domintell/module_directory.py
domintell/parser.py
domintell/connections/__init__.py
domintell/messages/__init__.py
domintell/messages/ai_status.py
domintell/messages/ao_status.py
domintell/messages/appinfo_request.py
domintell/messages/control.py
domintell/messages/dbir_status.py
domintell/messages/ddim_status.py
domintell/messages/di_status.py
domintell/messages/din10v_status.py
domintell/messages/dio_status.py
domintell/messages/dism_status.py
domintell/messages/dled_status.py
domintell/messages/dmov_status.py
domintell/messages/dmr_status.py
domintell/messages/do_status.py
domintell/messages/dpbu_status.py
domintell/messages/dtrp_status.py
domintell/messages/dtrv_status.py
domintell/messages/dtsc_status.py
domintell/messages/info.py
domintell/messages/login_request.py
domintell/messages/module_info.py
domintell/messages/module_status_request.py
domintell/messages/ping.py
domintell/messages/session_closed.py
domintell/messages/session_opened.py
domintell/messages/session_timeout.py
domintell/messages/set_ao.py
domintell/messages/set_di.py
domintell/messages/set_dimmer.py
domintell/messages/set_do.py
domintell/messages/set_temperature.py
domintell/messages/temperature_status.py
domintell/messages/var_status.py
domintell/modules/__init__.py
domintell/modules/ddim01.py
domintell/modules/dism0x.py
domintell/modules/do.py
domintell/modules/dpbu0x.py
domintell/modules/dtemp.py
domintell/utils/__init__.py
domintell/utils/encoders.py
python_domintell-0.0.17.dist-info/LICENSE
python_domintell-0.0.17.dist-info/METADATA
python_domintell-0.0.17.dist-info/WHEEL
python_domintell-0.0.17.dist-info/top_level.txt
python_domintell-0.0.17.dist-info/RECORD
