Metadata-Version: 2.1
Name: python-domintell
Version: 0.0.17
Summary: Python Library for the Domintell protocol
Home-page: https://github.com/shamanenas/python-domintell
Author: Zilvinas Binisevicius
Author-email: zilvinas@binis.me
License: MIT
Platform: any
Requires-Dist: pyserial
